elapse_secrets/__init__.py
elapse_secrets/db/__init__.py
elapse_secrets/db/rules-elapse-stable.yml
elapse_secrets/debug.py
elapse_secrets/main.py
elapse_secrets-0.1.2.dist-info/METADATA
elapse_secrets-0.1.2.dist-info/WHEEL
elapse_secrets-0.1.2.dist-info/RECORD
