Metadata-Version: 2.1
Name: elapse-secrets
Version: 0.1.2
Summary: Detects and removes sensitive information from the client-side to secure a user's data.
Author: kdcokenny
Author-email: kenny@kdco.llc
Requires-Python: >=3.10,<4.0
Classifier: Programming Language :: Python :: 3
Classifier: Programming Language :: Python :: 3.10
Classifier: Programming Language :: Python :: 3.11
Requires-Dist: pyyaml (>=6.0,<7.0)
